{
  "db_name": "PostgreSQL",
  "query": "\n            UPDATE memory\n            SET content = COALESCE($1, content),\n                importance = COALESCE($2, importance),\n                meta = COALESCE($3, meta)\n            WHERE id = $4\n            RETURNING\n                id,\n                account_id,\n                chat_id,\n                topic_id as \"topic_id: Uuid\",\n                type as \"type_!\",\n                content as \"content!\",\n                embedding as \"embedding: Vector\",\n                source_message_id,\n                importance as \"importance!\",\n                meta,\n                last_accessed_at as \"last_accessed_at!: jiff_sqlx::Timestamp\",\n                created_at as \"created_at!: jiff_sqlx::Timestamp\",\n                updated_at as \"updated_at!: jiff_sqlx::Timestamp\"\n            ",
  "describe": {
    "columns": [
      {
        "ordinal": 0,
        "name": "id",
        "type_info": "Uuid"
      },
      {
        "ordinal": 1,
        "name": "account_id",
        "type_info": "Int8"
      },
      {
        "ordinal": 2,
        "name": "chat_id",
        "type_info": "Int8"
      },
      {
        "ordinal": 3,
        "name": "topic_id: Uuid",
        "type_info": "Uuid"
      },
      {
        "ordinal": 4,
        "name": "type_!",
        "type_info": "Varchar"
      },
      {
        "ordinal": 5,
        "name": "content!",
        "type_info": "Text"
      },
      {
        "ordinal": 6,
        "name": "embedding: Vector",
        "type_info": {
          "Custom": {
            "name": "vector",
            "kind": "Simple"
          }
        }
      },
      {
        "ordinal": 7,
        "name": "source_message_id",
        "type_info": "Int8"
      },
      {
        "ordinal": 8,
        "name": "importance!",
        "type_info": "Int4"
      },
      {
        "ordinal": 9,
        "name": "meta",
        "type_info": "Jsonb"
      },
      {
        "ordinal": 10,
        "name": "last_accessed_at!: jiff_sqlx::Timestamp",
        "type_info": "Timestamptz"
      },
      {
        "ordinal": 11,
        "name": "created_at!: jiff_sqlx::Timestamp",
        "type_info": "Timestamptz"
      },
      {
        "ordinal": 12,
        "name": "updated_at!: jiff_sqlx::Timestamp",
        "type_info": "Timestamptz"
      }
    ],
    "parameters": {
      "Left": [
        "Text",
        "Int4",
        "Jsonb",
        "Uuid"
      ]
    },
    "nullable": [
      false,
      true,
      true,
      true,
      false,
      false,
      true,
      true,
      true,
      true,
      true,
      true,
      true
    ]
  },
  "hash": "407e623abb11638218efa6b292a9b9b0eb04e349fcb32a7bf273a5660bb49639"
}
